{"description":"Copy number variant detection from targeted dna sequencing","home_url":"https://github.com/etal/cnvkit/archive/daa6e19.tar.gz","id":"cnvkit","license":"Apache License 2.0","name":"cnvkit","toolclass":"CommandLineTool","total_pulls":0,"versions":[{"containers":[{"image":"quay.io/biocontainers/cnvkit:0.9.13--pyhdfd78af_0","type":"docker"},{"type":"singularity","url":"https://depot.galaxyproject.org/singularity/cnvkit:0.9.13--pyhdfd78af_0"},{"command":"conda install -c bioconda cnvkit=0.9.13","type":"conda"}],"last_updated":"Sat, 28 Mar 2026 05:20:55 -0000","version":"0.9.13"},{"containers":[{"image":"quay.io/biocontainers/cnvkit:0.9.12--pyhdfd78af_1","type":"docker"},{"type":"singularity","url":"https://depot.galaxyproject.org/singularity/cnvkit:0.9.12--pyhdfd78af_1"},{"command":"conda install -c bioconda cnvkit=0.9.12","type":"conda"},{"image":"quay.io/biocontainers/cnvkit:0.9.12--pyhdfd78af_0","type":"docker"},{"type":"singularity","url":"https://depot.galaxyproject.org/singularity/cnvkit:0.9.12--pyhdfd78af_0"}],"last_updated":"Sun, 29 Jun 2025 22:24:42 -0000","version":"0.9.12"},{"containers":[{"image":"quay.io/biocontainers/cnvkit:0.7.11--py27_0","type":"docker"},{"type":"singularity","url":"https://depot.galaxyproject.org/singularity/cnvkit:0.7.11--py27_0"},{"command":"conda install -c bioconda cnvkit=0.7.11","type":"conda"}],"last_updated":"Fri, 21 Jun 2024 20:31:23 -0000","version":"0.7.11"},{"containers":[{"image":"quay.io/biocontainers/cnvkit:0.8.0--py35_0","type":"docker"},{"type":"singularity","url":"https://depot.galaxyproject.org/singularity/cnvkit:0.8.0--py35_0"},{"command":"conda install -c bioconda cnvkit=0.8.0","type":"conda"}],"last_updated":"Fri, 21 Jun 2024 20:30:37 -0000","version":"0.8.0"},{"containers":[{"image":"quay.io/biocontainers/cnvkit:0.8.2--py35_0","type":"docker"},{"type":"singularity","url":"https://depot.galaxyproject.org/singularity/cnvkit:0.8.2--py35_0"},{"command":"conda install -c bioconda cnvkit=0.8.2","type":"conda"}],"last_updated":"Fri, 21 Jun 2024 20:29:35 -0000","version":"0.8.2"},{"containers":[{"image":"quay.io/biocontainers/cnvkit:0.8.3a0--py35_0","type":"docker"},{"type":"singularity","url":"https://depot.galaxyproject.org/singularity/cnvkit:0.8.3a0--py35_0"},{"command":"conda install -c bioconda cnvkit=0.8.3a0","type":"conda"},{"image":"quay.io/biocontainers/cnvkit:0.8.3a0--py35_1","type":"docker"},{"type":"singularity","url":"https://depot.galaxyproject.org/singularity/cnvkit:0.8.3a0--py35_1"}],"last_updated":"Fri, 21 Jun 2024 20:28:31 -0000","version":"0.8.3a0"},{"containers":[{"image":"quay.io/biocontainers/cnvkit:0.8.4--py35_0","type":"docker"},{"type":"singularity","url":"https://depot.galaxyproject.org/singularity/cnvkit:0.8.4--py35_0"},{"command":"conda install -c bioconda cnvkit=0.8.4","type":"conda"},{"image":"quay.io/biocontainers/cnvkit:0.8.4--py27_0","type":"docker"},{"type":"singularity","url":"https://depot.galaxyproject.org/singularity/cnvkit:0.8.4--py27_0"},{"image":"quay.io/biocontainers/cnvkit:0.8.4--py34_0","type":"docker"},{"type":"singularity","url":"https://depot.galaxyproject.org/singularity/cnvkit:0.8.4--py34_0"}],"last_updated":"Fri, 21 Jun 2024 20:26:35 -0000","version":"0.8.4"},{"containers":[{"image":"quay.io/biocontainers/cnvkit:0.8.5dev0--py27_0","type":"docker"},{"type":"singularity","url":"https://depot.galaxyproject.org/singularity/cnvkit:0.8.5dev0--py27_0"},{"command":"conda install -c bioconda cnvkit=0.8.5dev0","type":"conda"},{"image":"quay.io/biocontainers/cnvkit:0.8.5dev0--py34_0","type":"docker"},{"type":"singularity","url":"https://depot.galaxyproject.org/singularity/cnvkit:0.8.5dev0--py34_0"},{"image":"quay.io/biocontainers/cnvkit:0.8.5dev0--py35_0","type":"docker"},{"type":"singularity","url":"https://depot.galaxyproject.org/singularity/cnvkit:0.8.5dev0--py35_0"},{"image":"quay.io/biocontainers/cnvkit:0.8.5dev0--py27_1","type":"docker"},{"type":"singularity","url":"https://depot.galaxyproject.org/singularity/cnvkit:0.8.5dev0--py27_1"},{"image":"quay.io/biocontainers/cnvkit:0.8.5dev0--py34_1","type":"docker"},{"type":"singularity","url":"https://depot.galaxyproject.org/singularity/cnvkit:0.8.5dev0--py34_1"},{"image":"quay.io/biocontainers/cnvkit:0.8.5dev0--py35_1","type":"docker"},{"type":"singularity","url":"https://depot.galaxyproject.org/singularity/cnvkit:0.8.5dev0--py35_1"}],"last_updated":"Fri, 21 Jun 2024 20:24:07 -0000","version":"0.8.5dev0"},{"containers":[{"image":"quay.io/biocontainers/cnvkit:0.8.5--py35_0","type":"docker"},{"type":"singularity","url":"https://depot.galaxyproject.org/singularity/cnvkit:0.8.5--py35_0"},{"command":"conda install -c bioconda cnvkit=0.8.5","type":"conda"},{"image":"quay.io/biocontainers/cnvkit:0.8.5--py27_0","type":"docker"},{"type":"singularity","url":"https://depot.galaxyproject.org/singularity/cnvkit:0.8.5--py27_0"},{"image":"quay.io/biocontainers/cnvkit:0.8.5--py34_0","type":"docker"},{"type":"singularity","url":"https://depot.galaxyproject.org/singularity/cnvkit:0.8.5--py34_0"},{"image":"quay.io/biocontainers/cnvkit:0.8.5--py36_0","type":"docker"},{"type":"singularity","url":"https://depot.galaxyproject.org/singularity/cnvkit:0.8.5--py36_0"}],"last_updated":"Fri, 21 Jun 2024 20:18:05 -0000","version":"0.8.5"},{"containers":[{"image":"quay.io/biocontainers/cnvkit:0.8.6a0--py35_0","type":"docker"},{"type":"singularity","url":"https://depot.galaxyproject.org/singularity/cnvkit:0.8.6a0--py35_0"},{"command":"conda install -c bioconda cnvkit=0.8.6a0","type":"conda"},{"image":"quay.io/biocontainers/cnvkit:0.8.6a0--py27_0","type":"docker"},{"type":"singularity","url":"https://depot.galaxyproject.org/singularity/cnvkit:0.8.6a0--py27_0"},{"image":"quay.io/biocontainers/cnvkit:0.8.6a0--py27_1","type":"docker"},{"type":"singularity","url":"https://depot.galaxyproject.org/singularity/cnvkit:0.8.6a0--py27_1"},{"image":"quay.io/biocontainers/cnvkit:0.8.6a0--py35_1","type":"docker"},{"type":"singularity","url":"https://depot.galaxyproject.org/singularity/cnvkit:0.8.6a0--py35_1"},{"image":"quay.io/biocontainers/cnvkit:0.8.6a0--py35_2","type":"docker"},{"type":"singularity","url":"https://depot.galaxyproject.org/singularity/cnvkit:0.8.6a0--py35_2"},{"image":"quay.io/biocontainers/cnvkit:0.8.6a0--py27_2","type":"docker"},{"type":"singularity","url":"https://depot.galaxyproject.org/singularity/cnvkit:0.8.6a0--py27_2"},{"image":"quay.io/biocontainers/cnvkit:0.8.6a0--py36_2","type":"docker"},{"type":"singularity","url":"https://depot.galaxyproject.org/singularity/cnvkit:0.8.6a0--py36_2"}],"last_updated":"Fri, 21 Jun 2024 20:15:08 -0000","version":"0.8.6a0"},{"containers":[{"image":"quay.io/biocontainers/cnvkit:0.9.0--py27_0","type":"docker"},{"type":"singularity","url":"https://depot.galaxyproject.org/singularity/cnvkit:0.9.0--py27_0"},{"command":"conda install -c bioconda cnvkit=0.9.0","type":"conda"},{"image":"quay.io/biocontainers/cnvkit:0.9.0--py36_0","type":"docker"},{"type":"singularity","url":"https://depot.galaxyproject.org/singularity/cnvkit:0.9.0--py36_0"},{"image":"quay.io/biocontainers/cnvkit:0.9.0--py35_0","type":"docker"},{"type":"singularity","url":"https://depot.galaxyproject.org/singularity/cnvkit:0.9.0--py35_0"}],"last_updated":"Fri, 21 Jun 2024 20:08:58 -0000","version":"0.9.0"},{"containers":[{"image":"quay.io/biocontainers/cnvkit:0.9.1a0--py36_0","type":"docker"},{"type":"singularity","url":"https://depot.galaxyproject.org/singularity/cnvkit:0.9.1a0--py36_0"},{"command":"conda install -c bioconda cnvkit=0.9.1a0","type":"conda"},{"image":"quay.io/biocontainers/cnvkit:0.9.1a0--py35_0","type":"docker"},{"type":"singularity","url":"https://depot.galaxyproject.org/singularity/cnvkit:0.9.1a0--py35_0"},{"image":"quay.io/biocontainers/cnvkit:0.9.1a0--py27_0","type":"docker"},{"type":"singularity","url":"https://depot.galaxyproject.org/singularity/cnvkit:0.9.1a0--py27_0"}],"last_updated":"Fri, 21 Jun 2024 20:05:18 -0000","version":"0.9.1a0"},{"containers":[{"image":"quay.io/biocontainers/cnvkit:0.9.1--py27_0","type":"docker"},{"type":"singularity","url":"https://depot.galaxyproject.org/singularity/cnvkit:0.9.1--py27_0"},{"command":"conda install -c bioconda cnvkit=0.9.1","type":"conda"},{"image":"quay.io/biocontainers/cnvkit:0.9.1--py35_0","type":"docker"},{"type":"singularity","url":"https://depot.galaxyproject.org/singularity/cnvkit:0.9.1--py35_0"},{"image":"quay.io/biocontainers/cnvkit:0.9.1--py36_0","type":"docker"},{"type":"singularity","url":"https://depot.galaxyproject.org/singularity/cnvkit:0.9.1--py36_0"}],"last_updated":"Fri, 21 Jun 2024 20:01:39 -0000","version":"0.9.1"},{"containers":[{"image":"quay.io/biocontainers/cnvkit:0.9.2a0--py27_0","type":"docker"},{"type":"singularity","url":"https://depot.galaxyproject.org/singularity/cnvkit:0.9.2a0--py27_0"},{"command":"conda install -c bioconda cnvkit=0.9.2a0","type":"conda"},{"image":"quay.io/biocontainers/cnvkit:0.9.2a0--py36_0","type":"docker"},{"type":"singularity","url":"https://depot.galaxyproject.org/singularity/cnvkit:0.9.2a0--py36_0"},{"image":"quay.io/biocontainers/cnvkit:0.9.2a0--py35_0","type":"docker"},{"type":"singularity","url":"https://depot.galaxyproject.org/singularity/cnvkit:0.9.2a0--py35_0"},{"image":"quay.io/biocontainers/cnvkit:0.9.2a0--py35_1","type":"docker"},{"type":"singularity","url":"https://depot.galaxyproject.org/singularity/cnvkit:0.9.2a0--py35_1"},{"image":"quay.io/biocontainers/cnvkit:0.9.2a0--py27_1","type":"docker"},{"type":"singularity","url":"https://depot.galaxyproject.org/singularity/cnvkit:0.9.2a0--py27_1"},{"image":"quay.io/biocontainers/cnvkit:0.9.2a0--py36_1","type":"docker"},{"type":"singularity","url":"https://depot.galaxyproject.org/singularity/cnvkit:0.9.2a0--py36_1"},{"image":"quay.io/biocontainers/cnvkit:0.9.2a0--py36_2","type":"docker"},{"type":"singularity","url":"https://depot.galaxyproject.org/singularity/cnvkit:0.9.2a0--py36_2"},{"image":"quay.io/biocontainers/cnvkit:0.9.2a0--py27_2","type":"docker"},{"type":"singularity","url":"https://depot.galaxyproject.org/singularity/cnvkit:0.9.2a0--py27_2"},{"image":"quay.io/biocontainers/cnvkit:0.9.2a0--py35_2","type":"docker"},{"type":"singularity","url":"https://depot.galaxyproject.org/singularity/cnvkit:0.9.2a0--py35_2"}],"last_updated":"Fri, 21 Jun 2024 19:58:04 -0000","version":"0.9.2a0"},{"containers":[{"image":"quay.io/biocontainers/cnvkit:0.9.2--py27_2","type":"docker"},{"type":"singularity","url":"https://depot.galaxyproject.org/singularity/cnvkit:0.9.2--py27_2"},{"command":"conda install -c bioconda cnvkit=0.9.2","type":"conda"},{"image":"quay.io/biocontainers/cnvkit:0.9.2--py36_2","type":"docker"},{"type":"singularity","url":"https://depot.galaxyproject.org/singularity/cnvkit:0.9.2--py36_2"},{"image":"quay.io/biocontainers/cnvkit:0.9.2--py35_2","type":"docker"},{"type":"singularity","url":"https://depot.galaxyproject.org/singularity/cnvkit:0.9.2--py35_2"}],"last_updated":"Fri, 21 Jun 2024 19:50:06 -0000","version":"0.9.2"},{"containers":[{"image":"quay.io/biocontainers/cnvkit:0.9.3--py36_2","type":"docker"},{"type":"singularity","url":"https://depot.galaxyproject.org/singularity/cnvkit:0.9.3--py36_2"},{"command":"conda install -c bioconda cnvkit=0.9.3","type":"conda"},{"image":"quay.io/biocontainers/cnvkit:0.9.3--py35_2","type":"docker"},{"type":"singularity","url":"https://depot.galaxyproject.org/singularity/cnvkit:0.9.3--py35_2"},{"image":"quay.io/biocontainers/cnvkit:0.9.3--py27_2","type":"docker"},{"type":"singularity","url":"https://depot.galaxyproject.org/singularity/cnvkit:0.9.3--py27_2"}],"last_updated":"Fri, 21 Jun 2024 19:46:55 -0000","version":"0.9.3"},{"containers":[{"image":"quay.io/biocontainers/cnvkit:0.9.4a0--py27_0","type":"docker"},{"type":"singularity","url":"https://depot.galaxyproject.org/singularity/cnvkit:0.9.4a0--py27_0"},{"command":"conda install -c bioconda cnvkit=0.9.4a0","type":"conda"},{"image":"quay.io/biocontainers/cnvkit:0.9.4a0--py35_0","type":"docker"},{"type":"singularity","url":"https://depot.galaxyproject.org/singularity/cnvkit:0.9.4a0--py35_0"},{"image":"quay.io/biocontainers/cnvkit:0.9.4a0--py36_0","type":"docker"},{"type":"singularity","url":"https://depot.galaxyproject.org/singularity/cnvkit:0.9.4a0--py36_0"}],"last_updated":"Fri, 21 Jun 2024 19:43:44 -0000","version":"0.9.4a0"},{"containers":[{"image":"quay.io/biocontainers/cnvkit:0.9.5--py_0","type":"docker"},{"type":"singularity","url":"https://depot.galaxyproject.org/singularity/cnvkit:0.9.5--py_0"},{"command":"conda install -c bioconda cnvkit=0.9.5","type":"conda"},{"image":"quay.io/biocontainers/cnvkit:0.9.5--py35_1","type":"docker"},{"type":"singularity","url":"https://depot.galaxyproject.org/singularity/cnvkit:0.9.5--py35_1"},{"image":"quay.io/biocontainers/cnvkit:0.9.5--py36_1","type":"docker"},{"type":"singularity","url":"https://depot.galaxyproject.org/singularity/cnvkit:0.9.5--py36_1"},{"image":"quay.io/biocontainers/cnvkit:0.9.5--py27_1","type":"docker"},{"type":"singularity","url":"https://depot.galaxyproject.org/singularity/cnvkit:0.9.5--py27_1"}],"last_updated":"Fri, 21 Jun 2024 19:40:19 -0000","version":"0.9.5"},{"containers":[{"image":"quay.io/biocontainers/cnvkit:0.9.6a0--py27_0","type":"docker"},{"type":"singularity","url":"https://depot.galaxyproject.org/singularity/cnvkit:0.9.6a0--py27_0"},{"command":"conda install -c bioconda cnvkit=0.9.6a0","type":"conda"},{"image":"quay.io/biocontainers/cnvkit:0.9.6a0--py35_0","type":"docker"},{"type":"singularity","url":"https://depot.galaxyproject.org/singularity/cnvkit:0.9.6a0--py35_0"},{"image":"quay.io/biocontainers/cnvkit:0.9.6a0--py36_0","type":"docker"},{"type":"singularity","url":"https://depot.galaxyproject.org/singularity/cnvkit:0.9.6a0--py36_0"},{"image":"quay.io/biocontainers/cnvkit:0.9.6a0--py35_2","type":"docker"},{"type":"singularity","url":"https://depot.galaxyproject.org/singularity/cnvkit:0.9.6a0--py35_2"},{"image":"quay.io/biocontainers/cnvkit:0.9.6a0--py27_2","type":"docker"},{"type":"singularity","url":"https://depot.galaxyproject.org/singularity/cnvkit:0.9.6a0--py27_2"},{"image":"quay.io/biocontainers/cnvkit:0.9.6a0--py36_2","type":"docker"},{"type":"singularity","url":"https://depot.galaxyproject.org/singularity/cnvkit:0.9.6a0--py36_2"}],"last_updated":"Fri, 21 Jun 2024 19:36:08 -0000","version":"0.9.6a0"},{"containers":[{"image":"quay.io/biocontainers/cnvkit:0.9.6--py27_0","type":"docker"},{"type":"singularity","url":"https://depot.galaxyproject.org/singularity/cnvkit:0.9.6--py27_0"},{"command":"conda install -c bioconda cnvkit=0.9.6","type":"conda"},{"image":"quay.io/biocontainers/cnvkit:0.9.6--py27_1","type":"docker"},{"type":"singularity","url":"https://depot.galaxyproject.org/singularity/cnvkit:0.9.6--py27_1"},{"image":"quay.io/biocontainers/cnvkit:0.9.6--py36_1","type":"docker"},{"type":"singularity","url":"https://depot.galaxyproject.org/singularity/cnvkit:0.9.6--py36_1"},{"image":"quay.io/biocontainers/cnvkit:0.9.6--py37_1","type":"docker"},{"type":"singularity","url":"https://depot.galaxyproject.org/singularity/cnvkit:0.9.6--py37_1"},{"image":"quay.io/biocontainers/cnvkit:0.9.6--py_2","type":"docker"},{"type":"singularity","url":"https://depot.galaxyproject.org/singularity/cnvkit:0.9.6--py_2"}],"last_updated":"Fri, 21 Jun 2024 19:29:12 -0000","version":"0.9.6"},{"containers":[{"image":"quay.io/biocontainers/cnvkit:0.9.11--pyhdfd78af_0","type":"docker"},{"type":"singularity","url":"https://depot.galaxyproject.org/singularity/cnvkit:0.9.11--pyhdfd78af_0"},{"command":"conda install -c bioconda cnvkit=0.9.11","type":"conda"}],"last_updated":"Tue, 16 Apr 2024 00:16:11 -0000","version":"0.9.11"},{"containers":[{"image":"quay.io/biocontainers/cnvkit:0.9.10--pyhdfd78af_0","type":"docker"},{"type":"singularity","url":"https://depot.galaxyproject.org/singularity/cnvkit:0.9.10--pyhdfd78af_0"},{"command":"conda install -c bioconda cnvkit=0.9.10","type":"conda"}],"last_updated":"Tue, 28 Feb 2023 20:35:13 -0000","version":"0.9.10"},{"containers":[{"image":"quay.io/biocontainers/cnvkit:0.9.9--pyhdfd78af_0","type":"docker"},{"type":"singularity","url":"https://depot.galaxyproject.org/singularity/cnvkit:0.9.9--pyhdfd78af_0"},{"command":"conda install -c bioconda cnvkit=0.9.9","type":"conda"}],"last_updated":"Sat, 29 May 2021 09:13:20 -0000","version":"0.9.9"},{"containers":[{"image":"quay.io/biocontainers/cnvkit:0.9.8--py_0","type":"docker"},{"type":"singularity","url":"https://depot.galaxyproject.org/singularity/cnvkit:0.9.8--py_0"},{"command":"conda install -c bioconda cnvkit=0.9.8","type":"conda"}],"last_updated":"Tue, 15 Dec 2020 11:23:49 -0000","version":"0.9.8"},{"containers":[{"image":"quay.io/biocontainers/cnvkit:0.9.7--py_1","type":"docker"},{"type":"singularity","url":"https://depot.galaxyproject.org/singularity/cnvkit:0.9.7--py_1"},{"command":"conda install -c bioconda cnvkit=0.9.7","type":"conda"},{"image":"quay.io/biocontainers/cnvkit:0.9.7--pyh9f0ad1d_0","type":"docker"},{"type":"singularity","url":"https://depot.galaxyproject.org/singularity/cnvkit:0.9.7--pyh9f0ad1d_0"}],"last_updated":"Tue, 28 Jul 2020 05:08:46 -0000","version":"0.9.7"}]}