{"description":"Move component to top if it is one of the named ones. http://hgdownload.cse.ucsc.edu/admin/exe/","home_url":"","id":"ucsc-mafmefirst","license":"","name":"ucsc-mafmefirst","toolclass":"CommandLineTool","total_pulls":0,"versions":[{"containers":[{"image":"quay.io/biocontainers/ucsc-mafmefirst:482--h0b57e2e_0","type":"docker"},{"type":"singularity","url":"https://depot.galaxyproject.org/singularity/ucsc-mafmefirst:482--h0b57e2e_0"},{"command":"conda install -c bioconda ucsc-mafmefirst=482","type":"conda"}],"last_updated":"Sun, 29 Jun 2025 20:42:38 -0000","version":"482"},{"containers":[{"image":"quay.io/biocontainers/ucsc-mafmefirst:469--h664eb37_1","type":"docker"},{"type":"singularity","url":"https://depot.galaxyproject.org/singularity/ucsc-mafmefirst:469--h664eb37_1"},{"command":"conda install -c bioconda ucsc-mafmefirst=469","type":"conda"},{"image":"quay.io/biocontainers/ucsc-mafmefirst:469--h9b8f530_0","type":"docker"},{"type":"singularity","url":"https://depot.galaxyproject.org/singularity/ucsc-mafmefirst:469--h9b8f530_0"},{"command":"conda install -c bioconda ucsc-mafmefirst=469","type":"conda"}],"last_updated":"Fri, 13 Dec 2024 04:00:49 -0000","version":"469"},{"containers":[{"image":"quay.io/biocontainers/ucsc-mafmefirst:324--0","type":"docker"},{"type":"singularity","url":"https://depot.galaxyproject.org/singularity/ucsc-mafmefirst:324--0"},{"command":"conda install -c bioconda ucsc-mafmefirst=324","type":"conda"}],"last_updated":"Sat, 22 Jun 2024 01:29:55 -0000","version":"324"},{"containers":[{"image":"quay.io/biocontainers/ucsc-mafmefirst:357--1","type":"docker"},{"type":"singularity","url":"https://depot.galaxyproject.org/singularity/ucsc-mafmefirst:357--1"},{"command":"conda install -c bioconda ucsc-mafmefirst=357","type":"conda"}],"last_updated":"Sat, 22 Jun 2024 01:29:39 -0000","version":"357"},{"containers":[{"image":"quay.io/biocontainers/ucsc-mafmefirst:366--h5eb252a_0","type":"docker"},{"type":"singularity","url":"https://depot.galaxyproject.org/singularity/ucsc-mafmefirst:366--h5eb252a_0"},{"command":"conda install -c bioconda ucsc-mafmefirst=366","type":"conda"}],"last_updated":"Sat, 22 Jun 2024 01:29:27 -0000","version":"366"},{"containers":[{"image":"quay.io/biocontainers/ucsc-mafmefirst:377--h199ee4e_0","type":"docker"},{"type":"singularity","url":"https://depot.galaxyproject.org/singularity/ucsc-mafmefirst:377--h199ee4e_0"},{"command":"conda install -c bioconda ucsc-mafmefirst=377","type":"conda"},{"image":"quay.io/biocontainers/ucsc-mafmefirst:377--h0b8a92a_2","type":"docker"},{"type":"singularity","url":"https://depot.galaxyproject.org/singularity/ucsc-mafmefirst:377--h0b8a92a_2"},{"command":"conda install -c bioconda ucsc-mafmefirst=377","type":"conda"},{"image":"quay.io/biocontainers/ucsc-mafmefirst:377--h446ed27_1","type":"docker"},{"type":"singularity","url":"https://depot.galaxyproject.org/singularity/ucsc-mafmefirst:377--h446ed27_1"},{"command":"conda install -c bioconda ucsc-mafmefirst=377","type":"conda"}],"last_updated":"Sat, 22 Jun 2024 01:29:15 -0000","version":"377"}]}