{"description":"","home_url":"","id":"viennarna","license":"","name":"viennarna","toolclass":"CommandLineTool","total_pulls":0,"versions":[{"containers":[{"image":"quay.io/biocontainers/viennarna:2.7.2--py310pl5321h1111ac4_1","type":"docker"},{"type":"singularity","url":"https://depot.galaxyproject.org/singularity/viennarna:2.7.2--py310pl5321h1111ac4_1"},{"command":"conda install -c bioconda viennarna=2.7.2","type":"conda"},{"image":"quay.io/biocontainers/viennarna:2.7.2--py313pl5321h1f5d440_1","type":"docker"},{"type":"singularity","url":"https://depot.galaxyproject.org/singularity/viennarna:2.7.2--py313pl5321h1f5d440_1"},{"command":"conda install -c bioconda viennarna=2.7.2","type":"conda"},{"image":"quay.io/biocontainers/viennarna:2.7.2--py312pl5321h245ea3e_1","type":"docker"},{"type":"singularity","url":"https://depot.galaxyproject.org/singularity/viennarna:2.7.2--py312pl5321h245ea3e_1"},{"command":"conda install -c bioconda viennarna=2.7.2","type":"conda"},{"image":"quay.io/biocontainers/viennarna:2.7.2--py311pl5321hb7402bf_1","type":"docker"},{"type":"singularity","url":"https://depot.galaxyproject.org/singularity/viennarna:2.7.2--py311pl5321hb7402bf_1"},{"command":"conda install -c bioconda viennarna=2.7.2","type":"conda"},{"image":"quay.io/biocontainers/viennarna:2.7.2--py310pl5321haba5358_0","type":"docker"},{"type":"singularity","url":"https://depot.galaxyproject.org/singularity/viennarna:2.7.2--py310pl5321haba5358_0"},{"command":"conda install -c bioconda viennarna=2.7.2","type":"conda"},{"image":"quay.io/biocontainers/viennarna:2.7.2--py311pl5321h7f785ea_0","type":"docker"},{"type":"singularity","url":"https://depot.galaxyproject.org/singularity/viennarna:2.7.2--py311pl5321h7f785ea_0"},{"command":"conda install -c bioconda viennarna=2.7.2","type":"conda"},{"image":"quay.io/biocontainers/viennarna:2.7.2--py312pl5321h6f0ddca_0","type":"docker"},{"type":"singularity","url":"https://depot.galaxyproject.org/singularity/viennarna:2.7.2--py312pl5321h6f0ddca_0"},{"command":"conda install -c bioconda viennarna=2.7.2","type":"conda"},{"image":"quay.io/biocontainers/viennarna:2.7.2--py39pl5321h48c0b16_0","type":"docker"},{"type":"singularity","url":"https://depot.galaxyproject.org/singularity/viennarna:2.7.2--py39pl5321h48c0b16_0"},{"command":"conda install -c bioconda viennarna=2.7.2","type":"conda"}],"last_updated":"Fri, 20 Mar 2026 19:03:05 -0000","version":"2.7.2"},{"containers":[{"image":"quay.io/biocontainers/viennarna:2.7.1--py39pl5321h48c0b16_0","type":"docker"},{"type":"singularity","url":"https://depot.galaxyproject.org/singularity/viennarna:2.7.1--py39pl5321h48c0b16_0"},{"command":"conda install -c bioconda viennarna=2.7.1","type":"conda"},{"image":"quay.io/biocontainers/viennarna:2.7.1--py312pl5321h6f0ddca_0","type":"docker"},{"type":"singularity","url":"https://depot.galaxyproject.org/singularity/viennarna:2.7.1--py312pl5321h6f0ddca_0"},{"command":"conda install -c bioconda viennarna=2.7.1","type":"conda"},{"image":"quay.io/biocontainers/viennarna:2.7.1--py310pl5321haba5358_0","type":"docker"},{"type":"singularity","url":"https://depot.galaxyproject.org/singularity/viennarna:2.7.1--py310pl5321haba5358_0"},{"command":"conda install -c bioconda viennarna=2.7.1","type":"conda"},{"image":"quay.io/biocontainers/viennarna:2.7.1--py311pl5321h7f785ea_0","type":"docker"},{"type":"singularity","url":"https://depot.galaxyproject.org/singularity/viennarna:2.7.1--py311pl5321h7f785ea_0"},{"command":"conda install -c bioconda viennarna=2.7.1","type":"conda"}],"last_updated":"Mon, 15 Dec 2025 11:19:18 -0000","version":"2.7.1"},{"containers":[{"image":"quay.io/biocontainers/viennarna:2.7.0--py310pl5321haba5358_1","type":"docker"},{"type":"singularity","url":"https://depot.galaxyproject.org/singularity/viennarna:2.7.0--py310pl5321haba5358_1"},{"command":"conda install -c bioconda viennarna=2.7.0","type":"conda"},{"image":"quay.io/biocontainers/viennarna:2.7.0--py312pl5321h6f0ddca_1","type":"docker"},{"type":"singularity","url":"https://depot.galaxyproject.org/singularity/viennarna:2.7.0--py312pl5321h6f0ddca_1"},{"command":"conda install -c bioconda viennarna=2.7.0","type":"conda"},{"image":"quay.io/biocontainers/viennarna:2.7.0--py311pl5321h7f785ea_1","type":"docker"},{"type":"singularity","url":"https://depot.galaxyproject.org/singularity/viennarna:2.7.0--py311pl5321h7f785ea_1"},{"command":"conda install -c bioconda viennarna=2.7.0","type":"conda"},{"image":"quay.io/biocontainers/viennarna:2.7.0--py39pl5321h48c0b16_1","type":"docker"},{"type":"singularity","url":"https://depot.galaxyproject.org/singularity/viennarna:2.7.0--py39pl5321h48c0b16_1"},{"command":"conda install -c bioconda viennarna=2.7.0","type":"conda"},{"image":"quay.io/biocontainers/viennarna:2.7.0--py38pl5321hd78456e_0","type":"docker"},{"type":"singularity","url":"https://depot.galaxyproject.org/singularity/viennarna:2.7.0--py38pl5321hd78456e_0"},{"command":"conda install -c bioconda viennarna=2.7.0","type":"conda"},{"image":"quay.io/biocontainers/viennarna:2.7.0--py311pl5321h0f867f1_0","type":"docker"},{"type":"singularity","url":"https://depot.galaxyproject.org/singularity/viennarna:2.7.0--py311pl5321h0f867f1_0"},{"command":"conda install -c bioconda viennarna=2.7.0","type":"conda"},{"image":"quay.io/biocontainers/viennarna:2.7.0--py39pl5321hc9faaad_0","type":"docker"},{"type":"singularity","url":"https://depot.galaxyproject.org/singularity/viennarna:2.7.0--py39pl5321hc9faaad_0"},{"command":"conda install -c bioconda viennarna=2.7.0","type":"conda"},{"image":"quay.io/biocontainers/viennarna:2.7.0--py310pl5321head1c4d_0","type":"docker"},{"type":"singularity","url":"https://depot.galaxyproject.org/singularity/viennarna:2.7.0--py310pl5321head1c4d_0"},{"command":"conda install -c bioconda viennarna=2.7.0","type":"conda"},{"image":"quay.io/biocontainers/viennarna:2.7.0--py312pl5321h9f0f9fd_0","type":"docker"},{"type":"singularity","url":"https://depot.galaxyproject.org/singularity/viennarna:2.7.0--py312pl5321h9f0f9fd_0"},{"command":"conda install -c bioconda viennarna=2.7.0","type":"conda"}],"last_updated":"Tue, 10 Dec 2024 05:13:45 -0000","version":"2.7.0"},{"containers":[{"image":"quay.io/biocontainers/viennarna:2.6.4--py39pl5321hc9faaad_3","type":"docker"},{"type":"singularity","url":"https://depot.galaxyproject.org/singularity/viennarna:2.6.4--py39pl5321hc9faaad_3"},{"command":"conda install -c bioconda viennarna=2.6.4","type":"conda"},{"image":"quay.io/biocontainers/viennarna:2.6.4--py310pl5321head1c4d_3","type":"docker"},{"type":"singularity","url":"https://depot.galaxyproject.org/singularity/viennarna:2.6.4--py310pl5321head1c4d_3"},{"command":"conda install -c bioconda viennarna=2.6.4","type":"conda"},{"image":"quay.io/biocontainers/viennarna:2.6.4--py311pl5321h0f867f1_3","type":"docker"},{"type":"singularity","url":"https://depot.galaxyproject.org/singularity/viennarna:2.6.4--py311pl5321h0f867f1_3"},{"command":"conda install -c bioconda viennarna=2.6.4","type":"conda"},{"image":"quay.io/biocontainers/viennarna:2.6.4--py38pl5321hd78456e_3","type":"docker"},{"type":"singularity","url":"https://depot.galaxyproject.org/singularity/viennarna:2.6.4--py38pl5321hd78456e_3"},{"command":"conda install -c bioconda viennarna=2.6.4","type":"conda"},{"image":"quay.io/biocontainers/viennarna:2.6.4--py312pl5321h9f0f9fd_3","type":"docker"},{"type":"singularity","url":"https://depot.galaxyproject.org/singularity/viennarna:2.6.4--py312pl5321h9f0f9fd_3"},{"command":"conda install -c bioconda viennarna=2.6.4","type":"conda"},{"image":"quay.io/biocontainers/viennarna:2.6.4--py310pl5321hdf79db3_2","type":"docker"},{"type":"singularity","url":"https://depot.galaxyproject.org/singularity/viennarna:2.6.4--py310pl5321hdf79db3_2"},{"command":"conda install -c bioconda viennarna=2.6.4","type":"conda"},{"image":"quay.io/biocontainers/viennarna:2.6.4--py312pl5321hc60241a_2","type":"docker"},{"type":"singularity","url":"https://depot.galaxyproject.org/singularity/viennarna:2.6.4--py312pl5321hc60241a_2"},{"command":"conda install -c bioconda viennarna=2.6.4","type":"conda"},{"image":"quay.io/biocontainers/viennarna:2.6.4--py39pl5321heaaa4ec_2","type":"docker"},{"type":"singularity","url":"https://depot.galaxyproject.org/singularity/viennarna:2.6.4--py39pl5321heaaa4ec_2"},{"command":"conda install -c bioconda viennarna=2.6.4","type":"conda"},{"image":"quay.io/biocontainers/viennarna:2.6.4--py38pl5321h40d3509_2","type":"docker"},{"type":"singularity","url":"https://depot.galaxyproject.org/singularity/viennarna:2.6.4--py38pl5321h40d3509_2"},{"command":"conda install -c bioconda viennarna=2.6.4","type":"conda"},{"image":"quay.io/biocontainers/viennarna:2.6.4--py311pl5321h6eedab3_2","type":"docker"},{"type":"singularity","url":"https://depot.galaxyproject.org/singularity/viennarna:2.6.4--py311pl5321h6eedab3_2"},{"command":"conda install -c bioconda viennarna=2.6.4","type":"conda"},{"image":"quay.io/biocontainers/viennarna:2.6.4--py310pl5321h6cc9453_1","type":"docker"},{"type":"singularity","url":"https://depot.galaxyproject.org/singularity/viennarna:2.6.4--py310pl5321h6cc9453_1"},{"command":"conda install -c bioconda viennarna=2.6.4","type":"conda"},{"image":"quay.io/biocontainers/viennarna:2.6.4--py38pl5321h5cf8b27_1","type":"docker"},{"type":"singularity","url":"https://depot.galaxyproject.org/singularity/viennarna:2.6.4--py38pl5321h5cf8b27_1"},{"command":"conda install -c bioconda viennarna=2.6.4","type":"conda"},{"image":"quay.io/biocontainers/viennarna:2.6.4--py39pl5321h4e691d4_1","type":"docker"},{"type":"singularity","url":"https://depot.galaxyproject.org/singularity/viennarna:2.6.4--py39pl5321h4e691d4_1"},{"command":"conda install -c bioconda viennarna=2.6.4","type":"conda"},{"image":"quay.io/biocontainers/viennarna:2.6.4--py39pl5321h4e691d4_0","type":"docker"},{"type":"singularity","url":"https://depot.galaxyproject.org/singularity/viennarna:2.6.4--py39pl5321h4e691d4_0"},{"command":"conda install -c bioconda viennarna=2.6.4","type":"conda"},{"image":"quay.io/biocontainers/viennarna:2.6.4--py38pl5321h5cf8b27_0","type":"docker"},{"type":"singularity","url":"https://depot.galaxyproject.org/singularity/viennarna:2.6.4--py38pl5321h5cf8b27_0"},{"command":"conda install -c bioconda viennarna=2.6.4","type":"conda"},{"image":"quay.io/biocontainers/viennarna:2.6.4--py310pl5321h6cc9453_0","type":"docker"},{"type":"singularity","url":"https://depot.galaxyproject.org/singularity/viennarna:2.6.4--py310pl5321h6cc9453_0"},{"command":"conda install -c bioconda viennarna=2.6.4","type":"conda"}],"last_updated":"Thu, 18 Jul 2024 12:12:17 -0000","version":"2.6.4"},{"containers":[{"image":"quay.io/biocontainers/viennarna:2.2.5--2","type":"docker"},{"type":"singularity","url":"https://depot.galaxyproject.org/singularity/viennarna:2.2.5--2"},{"command":"conda install -c bioconda viennarna=2.2.5","type":"conda"}],"last_updated":"Fri, 21 Jun 2024 14:43:49 -0000","version":"2.2.5"},{"containers":[{"image":"quay.io/biocontainers/viennarna:2.2.9--0","type":"docker"},{"type":"singularity","url":"https://depot.galaxyproject.org/singularity/viennarna:2.2.9--0"},{"command":"conda install -c bioconda viennarna=2.2.9","type":"conda"}],"last_updated":"Fri, 21 Jun 2024 14:43:37 -0000","version":"2.2.9"},{"containers":[{"image":"quay.io/biocontainers/viennarna:2.2.10--1","type":"docker"},{"type":"singularity","url":"https://depot.galaxyproject.org/singularity/viennarna:2.2.10--1"},{"command":"conda install -c bioconda viennarna=2.2.10","type":"conda"}],"last_updated":"Fri, 21 Jun 2024 14:43:25 -0000","version":"2.2.10"},{"containers":[{"image":"quay.io/biocontainers/viennarna:2.3.0--1","type":"docker"},{"type":"singularity","url":"https://depot.galaxyproject.org/singularity/viennarna:2.3.0--1"},{"command":"conda install -c bioconda viennarna=2.3.0","type":"conda"}],"last_updated":"Fri, 21 Jun 2024 14:43:13 -0000","version":"2.3.0"},{"containers":[{"image":"quay.io/biocontainers/viennarna:2.3.1--0","type":"docker"},{"type":"singularity","url":"https://depot.galaxyproject.org/singularity/viennarna:2.3.1--0"},{"command":"conda install -c bioconda viennarna=2.3.1","type":"conda"},{"image":"quay.io/biocontainers/viennarna:2.3.1--1","type":"docker"},{"type":"singularity","url":"https://depot.galaxyproject.org/singularity/viennarna:2.3.1--1"},{"command":"conda install -c bioconda viennarna=2.3.1","type":"conda"}],"last_updated":"Fri, 21 Jun 2024 14:43:01 -0000","version":"2.3.1"},{"containers":[{"image":"quay.io/biocontainers/viennarna:2.3.2--0","type":"docker"},{"type":"singularity","url":"https://depot.galaxyproject.org/singularity/viennarna:2.3.2--0"},{"command":"conda install -c bioconda viennarna=2.3.2","type":"conda"}],"last_updated":"Fri, 21 Jun 2024 14:42:36 -0000","version":"2.3.2"},{"containers":[{"image":"quay.io/biocontainers/viennarna:2.3.3--0","type":"docker"},{"type":"singularity","url":"https://depot.galaxyproject.org/singularity/viennarna:2.3.3--0"},{"command":"conda install -c bioconda viennarna=2.3.3","type":"conda"}],"last_updated":"Fri, 21 Jun 2024 14:42:25 -0000","version":"2.3.3"},{"containers":[{"image":"quay.io/biocontainers/viennarna:2.3.5--0","type":"docker"},{"type":"singularity","url":"https://depot.galaxyproject.org/singularity/viennarna:2.3.5--0"},{"command":"conda install -c bioconda viennarna=2.3.5","type":"conda"}],"last_updated":"Fri, 21 Jun 2024 14:42:12 -0000","version":"2.3.5"},{"containers":[{"image":"quay.io/biocontainers/viennarna:2.4.1--0","type":"docker"},{"type":"singularity","url":"https://depot.galaxyproject.org/singularity/viennarna:2.4.1--0"},{"command":"conda install -c bioconda viennarna=2.4.1","type":"conda"},{"image":"quay.io/biocontainers/viennarna:2.4.1--1","type":"docker"},{"type":"singularity","url":"https://depot.galaxyproject.org/singularity/viennarna:2.4.1--1"},{"command":"conda install -c bioconda viennarna=2.4.1","type":"conda"}],"last_updated":"Fri, 21 Jun 2024 14:41:47 -0000","version":"2.4.1"},{"containers":[{"image":"quay.io/biocontainers/viennarna:2.4.2--1","type":"docker"},{"type":"singularity","url":"https://depot.galaxyproject.org/singularity/viennarna:2.4.2--1"},{"command":"conda install -c bioconda viennarna=2.4.2","type":"conda"}],"last_updated":"Fri, 21 Jun 2024 14:41:10 -0000","version":"2.4.2"},{"containers":[{"image":"quay.io/biocontainers/viennarna:2.4.3--0","type":"docker"},{"type":"singularity","url":"https://depot.galaxyproject.org/singularity/viennarna:2.4.3--0"},{"command":"conda install -c bioconda viennarna=2.4.3","type":"conda"}],"last_updated":"Fri, 21 Jun 2024 14:40:57 -0000","version":"2.4.3"},{"containers":[{"image":"quay.io/biocontainers/viennarna:2.4.4--0","type":"docker"},{"type":"singularity","url":"https://depot.galaxyproject.org/singularity/viennarna:2.4.4--0"},{"command":"conda install -c bioconda viennarna=2.4.4","type":"conda"},{"image":"quay.io/biocontainers/viennarna:2.4.4--1","type":"docker"},{"type":"singularity","url":"https://depot.galaxyproject.org/singularity/viennarna:2.4.4--1"},{"command":"conda install -c bioconda viennarna=2.4.4","type":"conda"}],"last_updated":"Fri, 21 Jun 2024 14:40:43 -0000","version":"2.4.4"},{"containers":[{"image":"quay.io/biocontainers/viennarna:2.4.5--1","type":"docker"},{"type":"singularity","url":"https://depot.galaxyproject.org/singularity/viennarna:2.4.5--1"},{"command":"conda install -c bioconda viennarna=2.4.5","type":"conda"},{"image":"quay.io/biocontainers/viennarna:2.4.5--0","type":"docker"},{"type":"singularity","url":"https://depot.galaxyproject.org/singularity/viennarna:2.4.5--0"},{"command":"conda install -c bioconda viennarna=2.4.5","type":"conda"},{"image":"quay.io/biocontainers/viennarna:2.4.5--py36hd28b015_2","type":"docker"},{"type":"singularity","url":"https://depot.galaxyproject.org/singularity/viennarna:2.4.5--py36hd28b015_2"},{"command":"conda install -c bioconda viennarna=2.4.5","type":"conda"},{"image":"quay.io/biocontainers/viennarna:2.4.5--py37hd28b015_3","type":"docker"},{"type":"singularity","url":"https://depot.galaxyproject.org/singularity/viennarna:2.4.5--py37hd28b015_3"},{"command":"conda install -c bioconda viennarna=2.4.5","type":"conda"}],"last_updated":"Fri, 21 Jun 2024 14:40:15 -0000","version":"2.4.5"},{"containers":[{"image":"quay.io/biocontainers/viennarna:2.4.6--0","type":"docker"},{"type":"singularity","url":"https://depot.galaxyproject.org/singularity/viennarna:2.4.6--0"},{"command":"conda install -c bioconda viennarna=2.4.6","type":"conda"}],"last_updated":"Fri, 21 Jun 2024 14:39:48 -0000","version":"2.4.6"},{"containers":[{"image":"quay.io/biocontainers/viennarna:2.4.7--py36_2","type":"docker"},{"type":"singularity","url":"https://depot.galaxyproject.org/singularity/viennarna:2.4.7--py36_2"},{"command":"conda install -c bioconda viennarna=2.4.7","type":"conda"},{"image":"quay.io/biocontainers/viennarna:2.4.7--py27_2","type":"docker"},{"type":"singularity","url":"https://depot.galaxyproject.org/singularity/viennarna:2.4.7--py27_2"},{"command":"conda install -c bioconda viennarna=2.4.7","type":"conda"},{"image":"quay.io/biocontainers/viennarna:2.4.7--py35_2","type":"docker"},{"type":"singularity","url":"https://depot.galaxyproject.org/singularity/viennarna:2.4.7--py35_2"},{"command":"conda install -c bioconda viennarna=2.4.7","type":"conda"},{"image":"quay.io/biocontainers/viennarna:2.4.7--py35_3","type":"docker"},{"type":"singularity","url":"https://depot.galaxyproject.org/singularity/viennarna:2.4.7--py35_3"},{"command":"conda install -c bioconda viennarna=2.4.7","type":"conda"},{"image":"quay.io/biocontainers/viennarna:2.4.7--py36_3","type":"docker"},{"type":"singularity","url":"https://depot.galaxyproject.org/singularity/viennarna:2.4.7--py36_3"},{"command":"conda install -c bioconda viennarna=2.4.7","type":"conda"},{"image":"quay.io/biocontainers/viennarna:2.4.7--py27_3","type":"docker"},{"type":"singularity","url":"https://depot.galaxyproject.org/singularity/viennarna:2.4.7--py27_3"},{"command":"conda install -c bioconda viennarna=2.4.7","type":"conda"},{"image":"quay.io/biocontainers/viennarna:2.4.7--py36_5","type":"docker"},{"type":"singularity","url":"https://depot.galaxyproject.org/singularity/viennarna:2.4.7--py36_5"},{"command":"conda install -c bioconda viennarna=2.4.7","type":"conda"},{"image":"quay.io/biocontainers/viennarna:2.4.7--py27_5","type":"docker"},{"type":"singularity","url":"https://depot.galaxyproject.org/singularity/viennarna:2.4.7--py27_5"},{"command":"conda install -c bioconda viennarna=2.4.7","type":"conda"},{"image":"quay.io/biocontainers/viennarna:2.4.7--py35_5","type":"docker"},{"type":"singularity","url":"https://depot.galaxyproject.org/singularity/viennarna:2.4.7--py35_5"},{"command":"conda install -c bioconda viennarna=2.4.7","type":"conda"}],"last_updated":"Fri, 21 Jun 2024 14:39:33 -0000","version":"2.4.7"},{"containers":[{"image":"quay.io/biocontainers/viennarna:2.4.8--py35_0","type":"docker"},{"type":"singularity","url":"https://depot.galaxyproject.org/singularity/viennarna:2.4.8--py35_0"},{"command":"conda install -c bioconda viennarna=2.4.8","type":"conda"},{"image":"quay.io/biocontainers/viennarna:2.4.8--py36_0","type":"docker"},{"type":"singularity","url":"https://depot.galaxyproject.org/singularity/viennarna:2.4.8--py36_0"},{"command":"conda install -c bioconda viennarna=2.4.8","type":"conda"},{"image":"quay.io/biocontainers/viennarna:2.4.8--py27_0","type":"docker"},{"type":"singularity","url":"https://depot.galaxyproject.org/singularity/viennarna:2.4.8--py27_0"},{"command":"conda install -c bioconda viennarna=2.4.8","type":"conda"},{"image":"quay.io/biocontainers/viennarna:2.4.8--py36hd28b015_1","type":"docker"},{"type":"singularity","url":"https://depot.galaxyproject.org/singularity/viennarna:2.4.8--py36hd28b015_1"},{"command":"conda install -c bioconda viennarna=2.4.8","type":"conda"},{"image":"quay.io/biocontainers/viennarna:2.4.8--py27hd28b015_1","type":"docker"},{"type":"singularity","url":"https://depot.galaxyproject.org/singularity/viennarna:2.4.8--py27hd28b015_1"},{"command":"conda install -c bioconda viennarna=2.4.8","type":"conda"},{"image":"quay.io/biocontainers/viennarna:2.4.8--py35hd28b015_1","type":"docker"},{"type":"singularity","url":"https://depot.galaxyproject.org/singularity/viennarna:2.4.8--py35hd28b015_1"},{"command":"conda install -c bioconda viennarna=2.4.8","type":"conda"},{"image":"quay.io/biocontainers/viennarna:2.4.8--py27hd28b015_2","type":"docker"},{"type":"singularity","url":"https://depot.galaxyproject.org/singularity/viennarna:2.4.8--py27hd28b015_2"},{"command":"conda install -c bioconda viennarna=2.4.8","type":"conda"},{"image":"quay.io/biocontainers/viennarna:2.4.8--py35hd28b015_2","type":"docker"},{"type":"singularity","url":"https://depot.galaxyproject.org/singularity/viennarna:2.4.8--py35hd28b015_2"},{"command":"conda install -c bioconda viennarna=2.4.8","type":"conda"},{"image":"quay.io/biocontainers/viennarna:2.4.8--py36hd28b015_2","type":"docker"},{"type":"singularity","url":"https://depot.galaxyproject.org/singularity/viennarna:2.4.8--py36hd28b015_2"},{"command":"conda install -c bioconda viennarna=2.4.8","type":"conda"}],"last_updated":"Fri, 21 Jun 2024 14:36:53 -0000","version":"2.4.8"},{"containers":[{"image":"quay.io/biocontainers/viennarna:2.4.9--py27hd28b015_0","type":"docker"},{"type":"singularity","url":"https://depot.galaxyproject.org/singularity/viennarna:2.4.9--py27hd28b015_0"},{"command":"conda install -c bioconda viennarna=2.4.9","type":"conda"},{"image":"quay.io/biocontainers/viennarna:2.4.9--py36hd28b015_0","type":"docker"},{"type":"singularity","url":"https://depot.galaxyproject.org/singularity/viennarna:2.4.9--py36hd28b015_0"},{"command":"conda install -c bioconda viennarna=2.4.9","type":"conda"},{"image":"quay.io/biocontainers/viennarna:2.4.9--py35hd28b015_0","type":"docker"},{"type":"singularity","url":"https://depot.galaxyproject.org/singularity/viennarna:2.4.9--py35hd28b015_0"},{"command":"conda install -c bioconda viennarna=2.4.9","type":"conda"}],"last_updated":"Fri, 21 Jun 2024 14:33:36 -0000","version":"2.4.9"},{"containers":[{"image":"quay.io/biocontainers/viennarna:1.8.5--h470a237_1","type":"docker"},{"type":"singularity","url":"https://depot.galaxyproject.org/singularity/viennarna:1.8.5--h470a237_1"},{"command":"conda install -c bioconda viennarna=1.8.5","type":"conda"}],"last_updated":"Fri, 21 Jun 2024 14:32:10 -0000","version":"1.8.5"},{"containers":[{"image":"quay.io/biocontainers/viennarna:2.4.11--py27hd28b015_0","type":"docker"},{"type":"singularity","url":"https://depot.galaxyproject.org/singularity/viennarna:2.4.11--py27hd28b015_0"},{"command":"conda install -c bioconda viennarna=2.4.11","type":"conda"},{"image":"quay.io/biocontainers/viennarna:2.4.11--py35hd28b015_0","type":"docker"},{"type":"singularity","url":"https://depot.galaxyproject.org/singularity/viennarna:2.4.11--py35hd28b015_0"},{"command":"conda install -c bioconda viennarna=2.4.11","type":"conda"},{"image":"quay.io/biocontainers/viennarna:2.4.11--py36hd28b015_0","type":"docker"},{"type":"singularity","url":"https://depot.galaxyproject.org/singularity/viennarna:2.4.11--py36hd28b015_0"},{"command":"conda install -c bioconda viennarna=2.4.11","type":"conda"},{"image":"quay.io/biocontainers/viennarna:2.4.11--py37hdbcaa40_1","type":"docker"},{"type":"singularity","url":"https://depot.galaxyproject.org/singularity/viennarna:2.4.11--py37hdbcaa40_1"},{"command":"conda install -c bioconda viennarna=2.4.11","type":"conda"},{"image":"quay.io/biocontainers/viennarna:2.4.11--py36hdbcaa40_1","type":"docker"},{"type":"singularity","url":"https://depot.galaxyproject.org/singularity/viennarna:2.4.11--py36hdbcaa40_1"},{"command":"conda install -c bioconda viennarna=2.4.11","type":"conda"},{"image":"quay.io/biocontainers/viennarna:2.4.11--py27hdbcaa40_1","type":"docker"},{"type":"singularity","url":"https://depot.galaxyproject.org/singularity/viennarna:2.4.11--py27hdbcaa40_1"},{"command":"conda install -c bioconda viennarna=2.4.11","type":"conda"},{"image":"quay.io/biocontainers/viennarna:2.4.11--py36hdbcaa40_2","type":"docker"},{"type":"singularity","url":"https://depot.galaxyproject.org/singularity/viennarna:2.4.11--py36hdbcaa40_2"},{"command":"conda install -c bioconda viennarna=2.4.11","type":"conda"},{"image":"quay.io/biocontainers/viennarna:2.4.11--py37hdbcaa40_2","type":"docker"},{"type":"singularity","url":"https://depot.galaxyproject.org/singularity/viennarna:2.4.11--py37hdbcaa40_2"},{"command":"conda install -c bioconda viennarna=2.4.11","type":"conda"},{"image":"quay.io/biocontainers/viennarna:2.4.11--py27hdbcaa40_2","type":"docker"},{"type":"singularity","url":"https://depot.galaxyproject.org/singularity/viennarna:2.4.11--py27hdbcaa40_2"},{"command":"conda install -c bioconda viennarna=2.4.11","type":"conda"}],"last_updated":"Fri, 21 Jun 2024 14:31:59 -0000","version":"2.4.11"},{"containers":[{"image":"quay.io/biocontainers/viennarna:2.4.13--py27hdbcaa40_2","type":"docker"},{"type":"singularity","url":"https://depot.galaxyproject.org/singularity/viennarna:2.4.13--py27hdbcaa40_2"},{"command":"conda install -c bioconda viennarna=2.4.13","type":"conda"},{"image":"quay.io/biocontainers/viennarna:2.4.13--py36hdbcaa40_2","type":"docker"},{"type":"singularity","url":"https://depot.galaxyproject.org/singularity/viennarna:2.4.13--py36hdbcaa40_2"},{"command":"conda install -c bioconda viennarna=2.4.13","type":"conda"},{"image":"quay.io/biocontainers/viennarna:2.4.13--py37hdbcaa40_2","type":"docker"},{"type":"singularity","url":"https://depot.galaxyproject.org/singularity/viennarna:2.4.13--py37hdbcaa40_2"},{"command":"conda install -c bioconda viennarna=2.4.13","type":"conda"}],"last_updated":"Fri, 21 Jun 2024 14:29:09 -0000","version":"2.4.13"},{"containers":[{"image":"quay.io/biocontainers/viennarna:2.4.14--py37h8b12597_0","type":"docker"},{"type":"singularity","url":"https://depot.galaxyproject.org/singularity/viennarna:2.4.14--py37h8b12597_0"},{"command":"conda install -c bioconda viennarna=2.4.14","type":"conda"},{"image":"quay.io/biocontainers/viennarna:2.4.14--py36h8b12597_0","type":"docker"},{"type":"singularity","url":"https://depot.galaxyproject.org/singularity/viennarna:2.4.14--py36h8b12597_0"},{"command":"conda install -c bioconda viennarna=2.4.14","type":"conda"},{"image":"quay.io/biocontainers/viennarna:2.4.14--py27h8b12597_0","type":"docker"},{"type":"singularity","url":"https://depot.galaxyproject.org/singularity/viennarna:2.4.14--py27h8b12597_0"},{"command":"conda install -c bioconda viennarna=2.4.14","type":"conda"},{"image":"quay.io/biocontainers/viennarna:2.4.14--py38h8162308_3","type":"docker"},{"type":"singularity","url":"https://depot.galaxyproject.org/singularity/viennarna:2.4.14--py38h8162308_3"},{"command":"conda install -c bioconda viennarna=2.4.14","type":"conda"},{"image":"quay.io/biocontainers/viennarna:2.4.14--py37h13b99d1_3","type":"docker"},{"type":"singularity","url":"https://depot.galaxyproject.org/singularity/viennarna:2.4.14--py37h13b99d1_3"},{"command":"conda install -c bioconda viennarna=2.4.14","type":"conda"},{"image":"quay.io/biocontainers/viennarna:2.4.14--py36hd181a71_3","type":"docker"},{"type":"singularity","url":"https://depot.galaxyproject.org/singularity/viennarna:2.4.14--py36hd181a71_3"},{"command":"conda install -c bioconda viennarna=2.4.14","type":"conda"},{"image":"quay.io/biocontainers/viennarna:2.4.14--py27heb12742_3","type":"docker"},{"type":"singularity","url":"https://depot.galaxyproject.org/singularity/viennarna:2.4.14--py27heb12742_3"},{"command":"conda install -c bioconda viennarna=2.4.14","type":"conda"},{"image":"quay.io/biocontainers/viennarna:2.4.14--py27heb12742_2","type":"docker"},{"type":"singularity","url":"https://depot.galaxyproject.org/singularity/viennarna:2.4.14--py27heb12742_2"},{"command":"conda install -c bioconda viennarna=2.4.14","type":"conda"},{"image":"quay.io/biocontainers/viennarna:2.4.14--py36hd181a71_2","type":"docker"},{"type":"singularity","url":"https://depot.galaxyproject.org/singularity/viennarna:2.4.14--py36hd181a71_2"},{"command":"conda install -c bioconda viennarna=2.4.14","type":"conda"},{"image":"quay.io/biocontainers/viennarna:2.4.14--py37h13b99d1_2","type":"docker"},{"type":"singularity","url":"https://depot.galaxyproject.org/singularity/viennarna:2.4.14--py37h13b99d1_2"},{"command":"conda install -c bioconda viennarna=2.4.14","type":"conda"},{"image":"quay.io/biocontainers/viennarna:2.4.14--py37h5202443_1","type":"docker"},{"type":"singularity","url":"https://depot.galaxyproject.org/singularity/viennarna:2.4.14--py37h5202443_1"},{"command":"conda install -c bioconda viennarna=2.4.14","type":"conda"},{"image":"quay.io/biocontainers/viennarna:2.4.14--py36hfa65bc7_1","type":"docker"},{"type":"singularity","url":"https://depot.galaxyproject.org/singularity/viennarna:2.4.14--py36hfa65bc7_1"},{"command":"conda install -c bioconda viennarna=2.4.14","type":"conda"}],"last_updated":"Fri, 21 Jun 2024 14:28:18 -0000","version":"2.4.14"},{"containers":[{"image":"quay.io/biocontainers/viennarna:2.6.3--py39pl5321h4e691d4_0","type":"docker"},{"type":"singularity","url":"https://depot.galaxyproject.org/singularity/viennarna:2.6.3--py39pl5321h4e691d4_0"},{"command":"conda install -c bioconda viennarna=2.6.3","type":"conda"},{"image":"quay.io/biocontainers/viennarna:2.6.3--py38pl5321h5cf8b27_0","type":"docker"},{"type":"singularity","url":"https://depot.galaxyproject.org/singularity/viennarna:2.6.3--py38pl5321h5cf8b27_0"},{"command":"conda install -c bioconda viennarna=2.6.3","type":"conda"},{"image":"quay.io/biocontainers/viennarna:2.6.3--py310pl5321h6cc9453_0","type":"docker"},{"type":"singularity","url":"https://depot.galaxyproject.org/singularity/viennarna:2.6.3--py310pl5321h6cc9453_0"},{"command":"conda install -c bioconda viennarna=2.6.3","type":"conda"}],"last_updated":"Sun, 23 Jul 2023 03:19:10 -0000","version":"2.6.3"},{"containers":[{"image":"quay.io/biocontainers/viennarna:2.6.2--py39pl5321h4e691d4_0","type":"docker"},{"type":"singularity","url":"https://depot.galaxyproject.org/singularity/viennarna:2.6.2--py39pl5321h4e691d4_0"},{"command":"conda install -c bioconda viennarna=2.6.2","type":"conda"},{"image":"quay.io/biocontainers/viennarna:2.6.2--py310pl5321h6cc9453_0","type":"docker"},{"type":"singularity","url":"https://depot.galaxyproject.org/singularity/viennarna:2.6.2--py310pl5321h6cc9453_0"},{"command":"conda install -c bioconda viennarna=2.6.2","type":"conda"},{"image":"quay.io/biocontainers/viennarna:2.6.2--py38pl5321h5cf8b27_0","type":"docker"},{"type":"singularity","url":"https://depot.galaxyproject.org/singularity/viennarna:2.6.2--py38pl5321h5cf8b27_0"},{"command":"conda install -c bioconda viennarna=2.6.2","type":"conda"}],"last_updated":"Fri, 30 Jun 2023 09:09:36 -0000","version":"2.6.2"},{"containers":[{"image":"quay.io/biocontainers/viennarna:2.5.1--py38pl5321h5cf8b27_2","type":"docker"},{"type":"singularity","url":"https://depot.galaxyproject.org/singularity/viennarna:2.5.1--py38pl5321h5cf8b27_2"},{"command":"conda install -c bioconda viennarna=2.5.1","type":"conda"},{"image":"quay.io/biocontainers/viennarna:2.5.1--py310pl5321h6cc9453_2","type":"docker"},{"type":"singularity","url":"https://depot.galaxyproject.org/singularity/viennarna:2.5.1--py310pl5321h6cc9453_2"},{"command":"conda install -c bioconda viennarna=2.5.1","type":"conda"},{"image":"quay.io/biocontainers/viennarna:2.5.1--py39pl5321h4e691d4_2","type":"docker"},{"type":"singularity","url":"https://depot.galaxyproject.org/singularity/viennarna:2.5.1--py39pl5321h4e691d4_2"},{"command":"conda install -c bioconda viennarna=2.5.1","type":"conda"},{"image":"quay.io/biocontainers/viennarna:2.5.1--py38pl5321h5cf8b27_1","type":"docker"},{"type":"singularity","url":"https://depot.galaxyproject.org/singularity/viennarna:2.5.1--py38pl5321h5cf8b27_1"},{"command":"conda install -c bioconda viennarna=2.5.1","type":"conda"},{"image":"quay.io/biocontainers/viennarna:2.5.1--py39pl5321h4e691d4_1","type":"docker"},{"type":"singularity","url":"https://depot.galaxyproject.org/singularity/viennarna:2.5.1--py39pl5321h4e691d4_1"},{"command":"conda install -c bioconda viennarna=2.5.1","type":"conda"},{"image":"quay.io/biocontainers/viennarna:2.5.1--py310pl5321h6cc9453_1","type":"docker"},{"type":"singularity","url":"https://depot.galaxyproject.org/singularity/viennarna:2.5.1--py310pl5321h6cc9453_1"},{"command":"conda install -c bioconda viennarna=2.5.1","type":"conda"},{"image":"quay.io/biocontainers/viennarna:2.5.1--py37pl5321h09c1ff4_1","type":"docker"},{"type":"singularity","url":"https://depot.galaxyproject.org/singularity/viennarna:2.5.1--py37pl5321h09c1ff4_1"},{"command":"conda install -c bioconda viennarna=2.5.1","type":"conda"},{"image":"quay.io/biocontainers/viennarna:2.5.1--py36pl5321hcac48a8_1","type":"docker"},{"type":"singularity","url":"https://depot.galaxyproject.org/singularity/viennarna:2.5.1--py36pl5321hcac48a8_1"},{"command":"conda install -c bioconda viennarna=2.5.1","type":"conda"},{"image":"quay.io/biocontainers/viennarna:2.5.1--py310pl5321hc8f18ef_1","type":"docker"},{"type":"singularity","url":"https://depot.galaxyproject.org/singularity/viennarna:2.5.1--py310pl5321hc8f18ef_1"},{"command":"conda install -c bioconda viennarna=2.5.1","type":"conda"},{"image":"quay.io/biocontainers/viennarna:2.5.1--py38pl5321h3b68952_1","type":"docker"},{"type":"singularity","url":"https://depot.galaxyproject.org/singularity/viennarna:2.5.1--py38pl5321h3b68952_1"},{"command":"conda install -c bioconda viennarna=2.5.1","type":"conda"},{"image":"quay.io/biocontainers/viennarna:2.5.1--py27pl5321h8f2a353_1","type":"docker"},{"type":"singularity","url":"https://depot.galaxyproject.org/singularity/viennarna:2.5.1--py27pl5321h8f2a353_1"},{"command":"conda install -c bioconda viennarna=2.5.1","type":"conda"},{"image":"quay.io/biocontainers/viennarna:2.5.1--py39pl5321h2add14b_1","type":"docker"},{"type":"singularity","url":"https://depot.galaxyproject.org/singularity/viennarna:2.5.1--py39pl5321h2add14b_1"},{"command":"conda install -c bioconda viennarna=2.5.1","type":"conda"},{"image":"quay.io/biocontainers/viennarna:2.5.1--py310pl5321hc8f18ef_0","type":"docker"},{"type":"singularity","url":"https://depot.galaxyproject.org/singularity/viennarna:2.5.1--py310pl5321hc8f18ef_0"},{"command":"conda install -c bioconda viennarna=2.5.1","type":"conda"},{"image":"quay.io/biocontainers/viennarna:2.5.1--py27pl5321h8f2a353_0","type":"docker"},{"type":"singularity","url":"https://depot.galaxyproject.org/singularity/viennarna:2.5.1--py27pl5321h8f2a353_0"},{"command":"conda install -c bioconda viennarna=2.5.1","type":"conda"},{"image":"quay.io/biocontainers/viennarna:2.5.1--py36pl5321hcac48a8_0","type":"docker"},{"type":"singularity","url":"https://depot.galaxyproject.org/singularity/viennarna:2.5.1--py36pl5321hcac48a8_0"},{"command":"conda install -c bioconda viennarna=2.5.1","type":"conda"},{"image":"quay.io/biocontainers/viennarna:2.5.1--py37pl5321h09c1ff4_0","type":"docker"},{"type":"singularity","url":"https://depot.galaxyproject.org/singularity/viennarna:2.5.1--py37pl5321h09c1ff4_0"},{"command":"conda install -c bioconda viennarna=2.5.1","type":"conda"},{"image":"quay.io/biocontainers/viennarna:2.5.1--py38pl5321h3b68952_0","type":"docker"},{"type":"singularity","url":"https://depot.galaxyproject.org/singularity/viennarna:2.5.1--py38pl5321h3b68952_0"},{"command":"conda install -c bioconda viennarna=2.5.1","type":"conda"},{"image":"quay.io/biocontainers/viennarna:2.5.1--py39pl5321h2add14b_0","type":"docker"},{"type":"singularity","url":"https://depot.galaxyproject.org/singularity/viennarna:2.5.1--py39pl5321h2add14b_0"},{"command":"conda install -c bioconda viennarna=2.5.1","type":"conda"}],"last_updated":"Tue, 16 May 2023 07:31:06 -0000","version":"2.5.1"},{"containers":[{"image":"quay.io/biocontainers/viennarna:2.5.0--py36pl5321hcac48a8_2","type":"docker"},{"type":"singularity","url":"https://depot.galaxyproject.org/singularity/viennarna:2.5.0--py36pl5321hcac48a8_2"},{"command":"conda install -c bioconda viennarna=2.5.0","type":"conda"},{"image":"quay.io/biocontainers/viennarna:2.5.0--py27pl5321h8f2a353_2","type":"docker"},{"type":"singularity","url":"https://depot.galaxyproject.org/singularity/viennarna:2.5.0--py27pl5321h8f2a353_2"},{"command":"conda install -c bioconda viennarna=2.5.0","type":"conda"},{"image":"quay.io/biocontainers/viennarna:2.5.0--py37pl5321h09c1ff4_2","type":"docker"},{"type":"singularity","url":"https://depot.galaxyproject.org/singularity/viennarna:2.5.0--py37pl5321h09c1ff4_2"},{"command":"conda install -c bioconda viennarna=2.5.0","type":"conda"},{"image":"quay.io/biocontainers/viennarna:2.5.0--py39pl5321h2add14b_2","type":"docker"},{"type":"singularity","url":"https://depot.galaxyproject.org/singularity/viennarna:2.5.0--py39pl5321h2add14b_2"},{"command":"conda install -c bioconda viennarna=2.5.0","type":"conda"},{"image":"quay.io/biocontainers/viennarna:2.5.0--py38pl5321h3b68952_2","type":"docker"},{"type":"singularity","url":"https://depot.galaxyproject.org/singularity/viennarna:2.5.0--py38pl5321h3b68952_2"},{"command":"conda install -c bioconda viennarna=2.5.0","type":"conda"},{"image":"quay.io/biocontainers/viennarna:2.5.0--py39pl5321h98c8e45_1","type":"docker"},{"type":"singularity","url":"https://depot.galaxyproject.org/singularity/viennarna:2.5.0--py39pl5321h98c8e45_1"},{"command":"conda install -c bioconda viennarna=2.5.0","type":"conda"},{"image":"quay.io/biocontainers/viennarna:2.5.0--py27pl5321h8eb80aa_1","type":"docker"},{"type":"singularity","url":"https://depot.galaxyproject.org/singularity/viennarna:2.5.0--py27pl5321h8eb80aa_1"},{"command":"conda install -c bioconda viennarna=2.5.0","type":"conda"},{"image":"quay.io/biocontainers/viennarna:2.5.0--py38pl5321h8e3bb3f_1","type":"docker"},{"type":"singularity","url":"https://depot.galaxyproject.org/singularity/viennarna:2.5.0--py38pl5321h8e3bb3f_1"},{"command":"conda install -c bioconda viennarna=2.5.0","type":"conda"},{"image":"quay.io/biocontainers/viennarna:2.5.0--py37pl5321hfecc14a_1","type":"docker"},{"type":"singularity","url":"https://depot.galaxyproject.org/singularity/viennarna:2.5.0--py37pl5321hfecc14a_1"},{"command":"conda install -c bioconda viennarna=2.5.0","type":"conda"},{"image":"quay.io/biocontainers/viennarna:2.5.0--py36pl5321h61628e2_1","type":"docker"},{"type":"singularity","url":"https://depot.galaxyproject.org/singularity/viennarna:2.5.0--py36pl5321h61628e2_1"},{"command":"conda install -c bioconda viennarna=2.5.0","type":"conda"},{"image":"quay.io/biocontainers/viennarna:2.5.0--py27h8eb80aa_0","type":"docker"},{"type":"singularity","url":"https://depot.galaxyproject.org/singularity/viennarna:2.5.0--py27h8eb80aa_0"},{"command":"conda install -c bioconda viennarna=2.5.0","type":"conda"},{"image":"quay.io/biocontainers/viennarna:2.5.0--py38h8e3bb3f_0","type":"docker"},{"type":"singularity","url":"https://depot.galaxyproject.org/singularity/viennarna:2.5.0--py38h8e3bb3f_0"},{"command":"conda install -c bioconda viennarna=2.5.0","type":"conda"},{"image":"quay.io/biocontainers/viennarna:2.5.0--py39h98c8e45_0","type":"docker"},{"type":"singularity","url":"https://depot.galaxyproject.org/singularity/viennarna:2.5.0--py39h98c8e45_0"},{"command":"conda install -c bioconda viennarna=2.5.0","type":"conda"},{"image":"quay.io/biocontainers/viennarna:2.5.0--py36h61628e2_0","type":"docker"},{"type":"singularity","url":"https://depot.galaxyproject.org/singularity/viennarna:2.5.0--py36h61628e2_0"},{"command":"conda install -c bioconda viennarna=2.5.0","type":"conda"},{"image":"quay.io/biocontainers/viennarna:2.5.0--py37hfecc14a_0","type":"docker"},{"type":"singularity","url":"https://depot.galaxyproject.org/singularity/viennarna:2.5.0--py37hfecc14a_0"},{"command":"conda install -c bioconda viennarna=2.5.0","type":"conda"}],"last_updated":"Wed, 23 Feb 2022 13:13:58 -0000","version":"2.5.0"},{"containers":[{"image":"quay.io/biocontainers/viennarna:2.4.18--py36h61628e2_0","type":"docker"},{"type":"singularity","url":"https://depot.galaxyproject.org/singularity/viennarna:2.4.18--py36h61628e2_0"},{"command":"conda install -c bioconda viennarna=2.4.18","type":"conda"},{"image":"quay.io/biocontainers/viennarna:2.4.18--py39h98c8e45_0","type":"docker"},{"type":"singularity","url":"https://depot.galaxyproject.org/singularity/viennarna:2.4.18--py39h98c8e45_0"},{"command":"conda install -c bioconda viennarna=2.4.18","type":"conda"},{"image":"quay.io/biocontainers/viennarna:2.4.18--py38h8e3bb3f_0","type":"docker"},{"type":"singularity","url":"https://depot.galaxyproject.org/singularity/viennarna:2.4.18--py38h8e3bb3f_0"},{"command":"conda install -c bioconda viennarna=2.4.18","type":"conda"},{"image":"quay.io/biocontainers/viennarna:2.4.18--py27h8eb80aa_0","type":"docker"},{"type":"singularity","url":"https://depot.galaxyproject.org/singularity/viennarna:2.4.18--py27h8eb80aa_0"},{"command":"conda install -c bioconda viennarna=2.4.18","type":"conda"},{"image":"quay.io/biocontainers/viennarna:2.4.18--py37hfecc14a_0","type":"docker"},{"type":"singularity","url":"https://depot.galaxyproject.org/singularity/viennarna:2.4.18--py37hfecc14a_0"},{"command":"conda install -c bioconda viennarna=2.4.18","type":"conda"}],"last_updated":"Tue, 04 May 2021 16:24:20 -0000","version":"2.4.18"},{"containers":[{"image":"quay.io/biocontainers/viennarna:2.4.17--py36h61628e2_1","type":"docker"},{"type":"singularity","url":"https://depot.galaxyproject.org/singularity/viennarna:2.4.17--py36h61628e2_1"},{"command":"conda install -c bioconda viennarna=2.4.17","type":"conda"},{"image":"quay.io/biocontainers/viennarna:2.4.17--py39h98c8e45_1","type":"docker"},{"type":"singularity","url":"https://depot.galaxyproject.org/singularity/viennarna:2.4.17--py39h98c8e45_1"},{"command":"conda install -c bioconda viennarna=2.4.17","type":"conda"},{"image":"quay.io/biocontainers/viennarna:2.4.17--py37hfecc14a_1","type":"docker"},{"type":"singularity","url":"https://depot.galaxyproject.org/singularity/viennarna:2.4.17--py37hfecc14a_1"},{"command":"conda install -c bioconda viennarna=2.4.17","type":"conda"},{"image":"quay.io/biocontainers/viennarna:2.4.17--py38h8e3bb3f_1","type":"docker"},{"type":"singularity","url":"https://depot.galaxyproject.org/singularity/viennarna:2.4.17--py38h8e3bb3f_1"},{"command":"conda install -c bioconda viennarna=2.4.17","type":"conda"},{"image":"quay.io/biocontainers/viennarna:2.4.17--py27h8eb80aa_1","type":"docker"},{"type":"singularity","url":"https://depot.galaxyproject.org/singularity/viennarna:2.4.17--py27h8eb80aa_1"},{"command":"conda install -c bioconda viennarna=2.4.17","type":"conda"},{"image":"quay.io/biocontainers/viennarna:2.4.17--py38h8162308_0","type":"docker"},{"type":"singularity","url":"https://depot.galaxyproject.org/singularity/viennarna:2.4.17--py38h8162308_0"},{"command":"conda install -c bioconda viennarna=2.4.17","type":"conda"},{"image":"quay.io/biocontainers/viennarna:2.4.17--py37h13b99d1_0","type":"docker"},{"type":"singularity","url":"https://depot.galaxyproject.org/singularity/viennarna:2.4.17--py37h13b99d1_0"},{"command":"conda install -c bioconda viennarna=2.4.17","type":"conda"},{"image":"quay.io/biocontainers/viennarna:2.4.17--py36hd181a71_0","type":"docker"},{"type":"singularity","url":"https://depot.galaxyproject.org/singularity/viennarna:2.4.17--py36hd181a71_0"},{"command":"conda install -c bioconda viennarna=2.4.17","type":"conda"},{"image":"quay.io/biocontainers/viennarna:2.4.17--py27heb12742_0","type":"docker"},{"type":"singularity","url":"https://depot.galaxyproject.org/singularity/viennarna:2.4.17--py27heb12742_0"},{"command":"conda install -c bioconda viennarna=2.4.17","type":"conda"}],"last_updated":"Thu, 25 Mar 2021 12:11:39 -0000","version":"2.4.17"},{"containers":[{"image":"quay.io/biocontainers/viennarna:2.4.15--py37h13b99d1_0","type":"docker"},{"type":"singularity","url":"https://depot.galaxyproject.org/singularity/viennarna:2.4.15--py37h13b99d1_0"},{"command":"conda install -c bioconda viennarna=2.4.15","type":"conda"},{"image":"quay.io/biocontainers/viennarna:2.4.15--py36hd181a71_0","type":"docker"},{"type":"singularity","url":"https://depot.galaxyproject.org/singularity/viennarna:2.4.15--py36hd181a71_0"},{"command":"conda install -c bioconda viennarna=2.4.15","type":"conda"},{"image":"quay.io/biocontainers/viennarna:2.4.15--py27heb12742_0","type":"docker"},{"type":"singularity","url":"https://depot.galaxyproject.org/singularity/viennarna:2.4.15--py27heb12742_0"},{"command":"conda install -c bioconda viennarna=2.4.15","type":"conda"},{"image":"quay.io/biocontainers/viennarna:2.4.15--py38h8162308_0","type":"docker"},{"type":"singularity","url":"https://depot.galaxyproject.org/singularity/viennarna:2.4.15--py38h8162308_0"},{"command":"conda install -c bioconda viennarna=2.4.15","type":"conda"}],"last_updated":"Tue, 01 Sep 2020 11:50:38 -0000","version":"2.4.15"}]}